pyarc/__init__.py
pyarc/cba.py
pyarc/algorithms/__init__.py
pyarc/algorithms/classifier.py
pyarc/algorithms/m1algorithm.py
pyarc/algorithms/m2algorithm.py
pyarc/algorithms/rule_algorithm.py
pyarc/algorithms/rule_generation.py
pyarc/data_structures/__init__.py
pyarc/data_structures/antecedent.py
pyarc/data_structures/appearance.py
pyarc/data_structures/car.py
pyarc/data_structures/comparable_itemset.py
pyarc/data_structures/consequent.py
pyarc/data_structures/item.py
pyarc/data_structures/transaction.py
pyarc/data_structures/transaction_db.py
pyarc/qcba/__init__.py
pyarc/qcba/classifier.py
pyarc/qcba/qcba.py
pyarc/qcba/transformation.py
pyarc/qcba/data_structures/__init__.py
pyarc/qcba/data_structures/interval.py
pyarc/qcba/data_structures/interval_reader.py
pyarc/qcba/data_structures/quant_dataset.py
pyarc/qcba/data_structures/quant_rule.py
pyarc/qcba/transforms/__init__.py
pyarc/qcba/transforms/extend.py
pyarc/qcba/transforms/overlap_prune.py
pyarc/qcba/transforms/postprune.py
pyarc/qcba/transforms/prune_literals.py
pyarc/qcba/transforms/refit.py
pyarc/qcba/transforms/trim.py
pyarc/utils/__init__.py
pyarc/utils/plotting.py
pyarc-1.1.4.dist-info/METADATA
pyarc-1.1.4.dist-info/WHEEL
pyarc-1.1.4.dist-info/top_level.txt
pyarc-1.1.4.dist-info/RECORD
