Metadata-Version: 2.1
Name: pyarc
Version: 1.1.4
Summary: An implementation of CBA algorithm
Home-page: https://github.com/jirifilip/pyARC
Author: Jiří Filip
Author-email: j.f.ilip@seznam.cz
License: UNKNOWN
Download-URL: https://github.com/jirifilip/pyARC/archive/1.0.tar.gz
Keywords: classification CBA association rules machine learning
Platform: UNKNOWN
Requires-Dist: pandas
Requires-Dist: numpy
Requires-Dist: sklearn
Requires-Dist: pyfim
